README.txt
setup.py
docs/HISTORY.txt
valentine/__init__.py
valentine.languagequery.egg-info/PKG-INFO
valentine.languagequery.egg-info/SOURCES.txt
valentine.languagequery.egg-info/dependency_links.txt
valentine.languagequery.egg-info/entry_points.txt
valentine.languagequery.egg-info/namespace_packages.txt
valentine.languagequery.egg-info/not-zip-safe
valentine.languagequery.egg-info/requires.txt
valentine.languagequery.egg-info/top_level.txt
valentine/languagequery/__init__.py
valentine/languagequery/configure.zcml
valentine/languagequery/patches.py