Metadata-Version: 1.0
Name: valentine.languagequery
Version: 1.1
Summary: Allows you to query for all languages if you are logged into Plone CMS.
Home-page: http://github.com/collective/valentine.languagequery
Author: UNKNOWN
Author-email: UNKNOWN
License: [GPL
Platform: UNKNOWN
Classifier: Programming Language :: Python
